{
  "query": "кредиты малому бизнесу",
  "engine": "YANDEX",
  "timestamp": "2025-05-21T03:58:23.142Z",
  "options": {
    "groupby": 10,
    "page": 4,
    "filter": 1,
    "within": 2,
    "loc": 213
  },
  "resultsCount": 10,
  "results": [
    {
      "title": "Открыть депозит для малого бизнеса в Калуге",
      "url": "https://www.rshb.ru/business/small/klg",
      "snippet": "Выгодные бизнес-вклады для малого, среднего и крупного бизнеса.",
      "domain": "",
      "position": 1
    },
    {
      "title": "17 банков готовы выдавать льготные кредиты малому...",
      "url": "https://mbgazeta.ru/arhiv/17-bankov-gotovy-vydavat-lgotnye-kredity-malomu-biznesu/",
      "snippet": "Минэкономразвития РФ завершило отбор банков для реализации программы льготного кредитования малого бизнеса «1764» v2.0.",
      "domain": "",
      "position": 1
    },
    {
      "title": "Кредитуем малый и средний бизнес для оптовой...",
      "url": "https://vk.com/wall-110937335_206499",
      "snippet": "Займ бизнесу ИП ООО на развитие • срочно • без залога - JetLend jetlend.ru.",
      "domain": "",
      "position": 1
    },
    {
      "title": "Виды кредитов для бизнеса: все о кредитовании для...",
      "url": "https://gradmsk.ru/video/bb7baae3bb46b249eec70f75e64ca848/",
      "snippet": "Как взять кредит предпринимателям для развития малого бизнеса.",
      "domain": "",
      "position": 1
    },
    {
      "title": "Бизнесовый кредит - мнение пользователя Алик о банке...",
      "url": "https://bankiros.ru/bank/tcs/otzyv/156558",
      "snippet": "Шесть месяцев это мало для таких вложений, но поддержка сказала что у бизнеса всегда сроки кредита меньше чем у физиком.",
      "domain": "",
      "position": 1
    },
    {
      "title": "Малые и средние препятствия – Коммерсантъ",
      "url": "https://www.kommersant.ru/doc/7675640",
      "snippet": "Кредитование малого и среднего предпринимательства (МСП) нельзя назвать драйвером роста кредитных портфелей банков...",
      "domain": "",
      "position": 1
    },
    {
      "title": "Кредит для малого бизнеса: существующие программы...",
      "url": "https://sps-sng.ru/index.php/biznes-idei/kreditovanie-malogo-biznesa-bez-zaloga-i-poruchitelej",
      "snippet": "Кредит для малого бизнеса отличается определенными требованиями к заемщику и, соответственно, условиями предоставления.",
      "domain": "",
      "position": 1
    },
    {
      "title": "ВТБ выдал первые кредиты МСП по новой льготной...",
      "url": "https://tass.ru/ekonomika/23823011",
      "snippet": "ВТБ предоставил льготные инвестиционные кредиты по новой программе Минэкономразвития России среднему и малому бизнесу из...",
      "domain": "",
      "position": 1
    },
    {
      "title": "В целях повышения доступности кредитов для малого...",
      "url": "https://www.raise-ranepa.ru/200525/novosti-vtb-kredit-dlya-yuridicheskih-lits/",
      "snippet": "ВТБ выдает кредиты на выплату зарплат представителям малого бизнеса или микропредприятий из пострадавших от коронавируса отраслей с...",
      "domain": "",
      "position": 1
    },
    {
      "title": "Сбербанк выдал более 230 миллионов рублей кредитов...",
      "url": "https://www.attestaciya-nok-r-f-pomoshch.ru/200525/novosti-sberbank-rf-malyj-biznes/",
      "snippet": "Условия в Сбербанке по кредитам для малого бизнеса зависят от программы кредитования, статуса заемщика в банке...",
      "domain": "",
      "position": 1
    }
  ]
}
